{
	"format_version": "1.12.0",
	"minecraft:geometry": [
		{
			"description": {
				"identifier": "geometry.combat_shotgun",
				"texture_width": 64,
				"texture_height": 64,
				"visible_bounds_width": 4,
				"visible_bounds_height": 3,
				"visible_bounds_offset": [0, 0.5, 0]
			},
			"bones": [
				{
					"name": "gun_body",
					"pivot": [0, -5.35, 0.2],
					"cubes": [
						{
							"origin": [-0.49419, -5.06228, 4.62074],
							"size": [0.98, 1.75, 1.5],
							"pivot": [-0.06419, -6.36228, 6.22074],
							"rotation": [22.5, 0, 0],
							"uv": {
								"north": {"uv": [20, 0], "uv_size": [1, 2]},
								"east": {"uv": [29, 4], "uv_size": [1.5, 2]},
								"south": {"uv": [2, 32], "uv_size": [1, 2]},
								"west": {"uv": [6, 29], "uv_size": [1.5, 2]},
								"up": {"uv": [31, 36], "uv_size": [1, 1.5]},
								"down": {"uv": [32, 37.5], "uv_size": [1, -1.5]}
							}
						},
						{
							"origin": [-0.00418, -6.12733, 1.40233],
							"size": [0, 1.5, 2.85],
							"uv": {
								"north": {"uv": [0, 0], "uv_size": [0, 1.5]},
								"east": {"uv": [26, 12], "uv_size": [3, 1.5]},
								"south": {"uv": [0, 0], "uv_size": [0, 1.5]},
								"up": {"uv": [0, 0], "uv_size": [0, 3]},
								"down": {"uv": [0, 3], "uv_size": [0, -3]}
							}
						},
						{
							"origin": [-0.19206, -5.17733, -7.34767],
							"size": [0.5, 0.5, 8],
							"pivot": [0.20795, -5.07733, -7.59767],
							"rotation": [0, 0, -45],
							"uv": {
								"north": {"uv": [9, 43], "uv_size": [0.5, 0.5]},
								"east": {"uv": [26, 18], "uv_size": [8, 0.5]},
								"south": {"uv": [43, 9], "uv_size": [0.5, 0.5]},
								"west": {"uv": [23, 26], "uv_size": [8, 0.5]},
								"up": {"uv": [10, 27], "uv_size": [0.5, 8]},
								"down": {"uv": [11, 35], "uv_size": [0.5, -8]}
							}
						},
						{
							"origin": [-0.55, -4.825, 1.5],
							"size": [1.1, 0.5, 3.1],
							"uv": {
								"north": {"uv": [3, 42], "uv_size": [1, 0.5]},
								"east": {"uv": [32, 26], "uv_size": [3, 0.5]},
								"south": {"uv": [42, 5], "uv_size": [1, 0.5]},
								"west": {"uv": [35, 33], "uv_size": [3, 0.5]},
								"up": {"uv": [18, 19], "uv_size": [1, 3]},
								"down": {"uv": [3, 31], "uv_size": [1, -3]}
							}
						},
						{
							"origin": [-0.2, -5.10233, -6.996],
							"size": [0.5, 1.5, 0.499],
							"uv": {
								"north": {"uv": [39, 26], "uv_size": [0.5, 1.5]},
								"east": {"uv": [28, 39], "uv_size": [0.5, 1.5]},
								"south": {"uv": [39, 28], "uv_size": [0.5, 1.5]},
								"west": {"uv": [29, 39], "uv_size": [0.5, 1.5]},
								"up": {"uv": [10, 43], "uv_size": [0.5, 0.5]},
								"down": {"uv": [43, 10.5], "uv_size": [0.5, -0.5]}
							}
						},
						{
							"origin": [1, -3.575, 1.5],
							"size": [0.25, 1, 3],
							"uv": {
								"north": {"uv": [42, 6], "uv_size": [0.5, 1]},
								"east": {"uv": [17, 4], "uv_size": [3, 1]},
								"south": {"uv": [8, 42], "uv_size": [0.5, 1]},
								"west": {"uv": [18, 29], "uv_size": [3, 1]},
								"up": {"uv": [33, 36], "uv_size": [0.5, 3]},
								"down": {"uv": [34, 39], "uv_size": [0.5, -3]}
							}
						},
						{
							"origin": [-1.25, -3.575, 1.5],
							"size": [0.25, 1, 3],
							"uv": {
								"north": {"uv": [6, 43], "uv_size": [0.5, 1]},
								"east": {"uv": [31, 8], "uv_size": [3, 1]},
								"south": {"uv": [43, 6], "uv_size": [0.5, 1]},
								"west": {"uv": [14, 31], "uv_size": [3, 1]},
								"up": {"uv": [38, 10], "uv_size": [0.5, 3]},
								"down": {"uv": [38, 16], "uv_size": [0.5, -3]}
							}
						},
						{
							"origin": [-0.875, -4.325, 4.5],
							"size": [1.75, 2, 1.25],
							"uv": {
								"north": {"uv": [26, 24], "uv_size": [2, 2]},
								"east": {"uv": [14, 29], "uv_size": [1.5, 2]},
								"south": {"uv": [14, 27], "uv_size": [2, 2]},
								"west": {"uv": [21, 29], "uv_size": [1.5, 2]},
								"up": {"uv": [23, 29], "uv_size": [2, 1.5]},
								"down": {"uv": [25, 30.5], "uv_size": [2, -1.5]}
							}
						},
						{
							"origin": [-0.875, -4.325, -0.5],
							"size": [1.75, 0.5, 5],
							"uv": {
								"north": {"uv": [39, 14], "uv_size": [2, 0.5]},
								"east": {"uv": [31, 27], "uv_size": [5, 0.5]},
								"south": {"uv": [39, 15], "uv_size": [2, 0.5]},
								"west": {"uv": [31, 28], "uv_size": [5, 0.5]},
								"up": {"uv": [6, 13], "uv_size": [2, 5]},
								"down": {"uv": [8, 19], "uv_size": [2, -5]}
							}
						},
						{
							"origin": [-0.75, -3.825, -0.5],
							"size": [1.5, 1.5, 1.75],
							"uv": {
								"north": {"uv": [34, 24], "uv_size": [1.5, 1.5]},
								"east": {"uv": [29, 30], "uv_size": [2, 1.5]},
								"south": {"uv": [26, 34], "uv_size": [1.5, 1.5]},
								"west": {"uv": [31, 4], "uv_size": [2, 1.5]},
								"up": {"uv": [6, 31], "uv_size": [1.5, 2]},
								"down": {"uv": [31, 8], "uv_size": [1.5, -2]}
							}
						},
						{
							"origin": [-0.50418, -4.025, 5.7],
							"size": [1, 1, 1.5],
							"pivot": [-0.00418, -3.525, 6.05],
							"rotation": [0, 0, -45],
							"uv": {
								"north": {"uv": [9, 11], "uv_size": [1, 1]},
								"east": {"uv": [21, 5], "uv_size": [1.5, 1]},
								"south": {"uv": [8, 13], "uv_size": [1, 1]},
								"west": {"uv": [24, 12], "uv_size": [1.5, 1]},
								"up": {"uv": [36, 34], "uv_size": [1, 1.5]},
								"down": {"uv": [35, 37.5], "uv_size": [1, -1.5]}
							}
						},
						{
							"origin": [-0.75, -2.325, -0.5],
							"size": [1.5, 0.5, 6.1],
							"uv": {
								"north": {"uv": [39, 30], "uv_size": [1.5, 0.5]},
								"east": {"uv": [29, 23], "uv_size": [6, 0.5]},
								"south": {"uv": [31, 39], "uv_size": [1.5, 0.5]},
								"west": {"uv": [27, 29], "uv_size": [6, 0.5]},
								"up": {"uv": [2, 16], "uv_size": [1.5, 6]},
								"down": {"uv": [4, 22], "uv_size": [1.5, -6]}
							}
						},
						{
							"origin": [-0.25, -1.825, -6.475],
							"size": [0.5, 0.2, 0.5],
							"uv": {
								"north": {"uv": [44, 6], "uv_size": [0.5, 0.5]},
								"east": {"uv": [7, 44], "uv_size": [0.5, 0.5]},
								"south": {"uv": [44, 7], "uv_size": [0.5, 0.5]},
								"west": {"uv": [8, 44], "uv_size": [0.5, 0.5]},
								"up": {"uv": [44, 8], "uv_size": [0.5, 0.5]},
								"down": {"uv": [9, 44.5], "uv_size": [0.5, -0.5]}
							}
						},
						{
							"origin": [-0.0375, -1.625, -6.425],
							"size": [0.075, 0.2, 0.3],
							"uv": {
								"north": {"uv": [44, 10], "uv_size": [0.5, 0.5]},
								"east": {"uv": [11, 44], "uv_size": [0.5, 0.5]},
								"south": {"uv": [44, 11], "uv_size": [0.5, 0.5]},
								"west": {"uv": [12, 44], "uv_size": [0.5, 0.5]},
								"up": {"uv": [44, 12], "uv_size": [0.5, 0.5]},
								"down": {"uv": [13, 44.5], "uv_size": [0.5, -0.5]}
							}
						},
						{
							"origin": [-0.25, -2.325, -6.475],
							"size": [0, 0.5, 0.5],
							"uv": {
								"north": {"uv": [0, 0], "uv_size": [0, 0.5]},
								"east": {"uv": [44, 9], "uv_size": [0.5, 0.5]},
								"south": {"uv": [0, 0], "uv_size": [0, 0.5]},
								"up": {"uv": [0, 0], "uv_size": [0, 0.5]},
								"down": {"uv": [0, 0.5], "uv_size": [0, -0.5]}
							}
						},
						{
							"origin": [0.25, -2.325, -6.475],
							"size": [0, 0.5, 0.5],
							"uv": {
								"north": {"uv": [0, 0], "uv_size": [0, 0.5]},
								"south": {"uv": [0, 0], "uv_size": [0, 0.5]},
								"west": {"uv": [10, 44], "uv_size": [0.5, 0.5]},
								"up": {"uv": [0, 0], "uv_size": [0, 0.5]},
								"down": {"uv": [0, 0.5], "uv_size": [0, -0.5]}
							}
						},
						{
							"origin": [-0.5, -1.825, 4.2],
							"size": [1, 0.175, 1.4],
							"uv": {
								"north": {"uv": [7, 43], "uv_size": [1, 0.5]},
								"east": {"uv": [41, 41], "uv_size": [1.5, 0.5]},
								"south": {"uv": [43, 7], "uv_size": [1, 0.5]},
								"west": {"uv": [42, 0], "uv_size": [1.5, 0.5]},
								"up": {"uv": [14, 38], "uv_size": [1, 1.5]},
								"down": {"uv": [15, 39.5], "uv_size": [1, -1.5]}
							}
						},
						{
							"origin": [-0.75, -3.575, 5.75],
							"size": [1.5, 1, 1],
							"uv": {
								"north": {"uv": [32, 21], "uv_size": [1.5, 1]},
								"east": {"uv": [16, 13], "uv_size": [1, 1]},
								"south": {"uv": [34, 8], "uv_size": [1.5, 1]},
								"west": {"uv": [16, 18], "uv_size": [1, 1]},
								"up": {"uv": [36, 30], "uv_size": [1.5, 1]},
								"down": {"uv": [36, 37], "uv_size": [1.5, -1]}
							}
						},
						{
							"origin": [-1.0129, -4.30387, -6.49642],
							"size": [2, 2, 5.5],
							"pivot": [0, -3.31677, 3.76791],
							"rotation": [0, 0, 45],
							"uv": {
								"north": {"uv": [18, 27], "uv_size": [2, 2]},
								"east": {"uv": [10, 8], "uv_size": [5.5, 2]},
								"south": {"uv": [23, 27], "uv_size": [2, 2]},
								"west": {"uv": [10, 10], "uv_size": [5.5, 2]},
								"up": {"uv": [0, 11], "uv_size": [2, 5.5]},
								"down": {"uv": [11, 5.5], "uv_size": [2, -5.5]}
							}
						},
						{
							"origin": [-1, -3.825, 1.25],
							"size": [2, 1.5, 3.25],
							"uv": {
								"north": {"uv": [19, 30], "uv_size": [2, 1.5]},
								"east": {"uv": [24, 19], "uv_size": [3.5, 1.5]},
								"south": {"uv": [27, 30], "uv_size": [2, 1.5]},
								"west": {"uv": [24, 21], "uv_size": [3.5, 1.5]},
								"up": {"uv": [14, 18], "uv_size": [2, 3.5]},
								"down": {"uv": [8, 22.5], "uv_size": [2, -3.5]}
							}
						},
						{
							"origin": [-0.5, -4.825, -0.5],
							"size": [1, 0.5, 2],
							"uv": {
								"north": {"uv": [42, 8], "uv_size": [1, 0.5]},
								"east": {"uv": [38, 19], "uv_size": [2, 0.5]},
								"south": {"uv": [9, 42], "uv_size": [1, 0.5]},
								"west": {"uv": [20, 38], "uv_size": [2, 0.5]},
								"up": {"uv": [16, 32], "uv_size": [1, 2]},
								"down": {"uv": [2, 38], "uv_size": [1, -2]}
							}
						},
						{
							"origin": [-0.5, -5.825, 0.5],
							"size": [1, 1, 1],
							"uv": {
								"north": {"uv": [39, 16], "uv_size": [1, 1]},
								"east": {"uv": [39, 17], "uv_size": [1, 1]},
								"south": {"uv": [39, 18], "uv_size": [1, 1]},
								"west": {"uv": [20, 39], "uv_size": [1, 1]},
								"up": {"uv": [39, 20], "uv_size": [1, 1]},
								"down": {"uv": [21, 40], "uv_size": [1, -1]}
							}
						},
						{
							"origin": [-0.73535, -4.01316, -6.99642],
							"size": [1.5, 1.5, 0.5],
							"pivot": [-0.03536, -3.26316, 1.34108],
							"rotation": [0, 0, 45],
							"uv": {
								"north": {"uv": [34, 21], "uv_size": [1.5, 1.5]},
								"east": {"uv": [19, 41], "uv_size": [0.5, 1.5]},
								"south": {"uv": [24, 34], "uv_size": [1.5, 1.5]},
								"west": {"uv": [41, 25], "uv_size": [0.5, 1.5]},
								"up": {"uv": [41, 27], "uv_size": [1.5, 0.5]},
								"down": {"uv": [28, 41.5], "uv_size": [1.5, -0.5]}
							}
						},
						{
							"origin": [-0.73535, -4.01316, -0.99642],
							"size": [1.5, 1.5, 0.5],
							"pivot": [-0.03536, -3.26316, 7.34108],
							"rotation": [0, 0, 45],
							"uv": {
								"north": {"uv": [28, 34], "uv_size": [1.5, 1.5]},
								"east": {"uv": [41, 30], "uv_size": [0.5, 1.5]},
								"south": {"uv": [34, 29], "uv_size": [1.5, 1.5]},
								"west": {"uv": [33, 41], "uv_size": [0.5, 1.5]},
								"up": {"uv": [41, 32], "uv_size": [1.5, 0.5]},
								"down": {"uv": [34, 41.5], "uv_size": [1.5, -0.5]}
							}
						},
						{
							"origin": [-0.35418, -3.875, -1.825],
							"size": [0.7, 0.6, 1.525],
							"uv": {
								"north": {"uv": [11, 43], "uv_size": [0.5, 0.5]},
								"east": {"uv": [39, 31], "uv_size": [1.5, 0.5]},
								"south": {"uv": [43, 11], "uv_size": [0.5, 0.5]},
								"west": {"uv": [39, 32], "uv_size": [1.5, 0.5]},
								"up": {"uv": [33, 39], "uv_size": [0.5, 1.5]},
								"down": {"uv": [39, 34.5], "uv_size": [0.5, -1.5]}
							}
						}
					]
				},
				{
					"name": "body",
					"parent": "gun_body",
					"pivot": [0, -5.35, 0.2]
				},
				{
					"name": "sights",
					"parent": "body",
					"pivot": [0, -0.95125, 12.0125],
					"cubes": [
						{
							"origin": [0.20832, -1.90233, 4.55233],
							"size": [0.175, 0.5, 0.625],
							"pivot": [0.29581, -1.65233, 4.86483],
							"rotation": [22.5, 0, 0],
							"uv": {
								"north": {"uv": [12, 43], "uv_size": [0.5, 0.5]},
								"east": {"uv": [43, 12], "uv_size": [0.5, 0.5]},
								"south": {"uv": [13, 43], "uv_size": [0.5, 0.5]},
								"west": {"uv": [43, 13], "uv_size": [0.5, 0.5]},
								"up": {"uv": [14, 43], "uv_size": [0.5, 0.5]},
								"down": {"uv": [43, 14.5], "uv_size": [0.5, -0.5]}
							}
						},
						{
							"origin": [0.20982, -1.77733, 4.40233],
							"size": [0.173, 0.25, 0.15],
							"uv": {
								"north": {"uv": [15, 43], "uv_size": [0.5, 0.5]},
								"east": {"uv": [43, 15], "uv_size": [0.5, 0.5]},
								"south": {"uv": [16, 43], "uv_size": [0.5, 0.5]},
								"west": {"uv": [43, 16], "uv_size": [0.5, 0.5]},
								"up": {"uv": [17, 43], "uv_size": [0.5, 0.5]},
								"down": {"uv": [43, 17.5], "uv_size": [0.5, -0.5]}
							}
						},
						{
							"origin": [-0.39119, -1.77733, 4.40233],
							"size": [0.173, 0.25, 0.15],
							"uv": {
								"north": {"uv": [18, 43], "uv_size": [0.5, 0.5]},
								"east": {"uv": [43, 18], "uv_size": [0.5, 0.5]},
								"south": {"uv": [19, 43], "uv_size": [0.5, 0.5]},
								"west": {"uv": [43, 19], "uv_size": [0.5, 0.5]},
								"up": {"uv": [20, 43], "uv_size": [0.5, 0.5]},
								"down": {"uv": [43, 20.5], "uv_size": [0.5, -0.5]}
							}
						},
						{
							"origin": [-0.39168, -1.90233, 4.55233],
							"size": [0.175, 0.5, 0.625],
							"pivot": [-0.30419, -1.65233, 4.86483],
							"rotation": [22.5, 0, 0],
							"uv": {
								"north": {"uv": [21, 43], "uv_size": [0.5, 0.5]},
								"east": {"uv": [43, 21], "uv_size": [0.5, 0.5]},
								"south": {"uv": [22, 43], "uv_size": [0.5, 0.5]},
								"west": {"uv": [43, 22], "uv_size": [0.5, 0.5]},
								"up": {"uv": [23, 43], "uv_size": [0.5, 0.5]},
								"down": {"uv": [43, 23.5], "uv_size": [0.5, -0.5]}
							}
						},
						{
							"origin": [-0.08702, -1.675, 4.876],
							"size": [0.16568, 0.1, 0.098],
							"pivot": [-0.00418, -1.475, 4.925],
							"rotation": [0, 0, 45],
							"uv": {
								"north": {"uv": [24, 43], "uv_size": [0.5, 0.5]},
								"east": {"uv": [43, 24], "uv_size": [0.5, 0.5]},
								"south": {"uv": [25, 43], "uv_size": [0.5, 0.5]},
								"west": {"uv": [43, 25], "uv_size": [0.5, 0.5]},
								"up": {"uv": [26, 43], "uv_size": [0.5, 0.5]},
								"down": {"uv": [43, 26.5], "uv_size": [0.5, -0.5]}
							}
						},
						{
							"origin": [-0.09953, -1.675, 4.875],
							"size": [0.19068, 0.1, 0.1],
							"uv": {
								"north": {"uv": [27, 43], "uv_size": [0.5, 0.5]},
								"east": {"uv": [43, 27], "uv_size": [0.5, 0.5]},
								"south": {"uv": [28, 43], "uv_size": [0.5, 0.5]},
								"west": {"uv": [43, 28], "uv_size": [0.5, 0.5]},
								"up": {"uv": [29, 43], "uv_size": [0.5, 0.5]},
								"down": {"uv": [43, 29.5], "uv_size": [0.5, -0.5]}
							}
						},
						{
							"origin": [-0.08702, -1.375, 4.876],
							"size": [0.16568, 0.1, 0.098],
							"pivot": [-0.00418, -1.475, 4.925],
							"rotation": [0, 0, 45],
							"uv": {
								"north": {"uv": [30, 43], "uv_size": [0.5, 0.5]},
								"east": {"uv": [43, 30], "uv_size": [0.5, 0.5]},
								"south": {"uv": [31, 43], "uv_size": [0.5, 0.5]},
								"west": {"uv": [43, 31], "uv_size": [0.5, 0.5]},
								"up": {"uv": [32, 43], "uv_size": [0.5, 0.5]},
								"down": {"uv": [43, 32.5], "uv_size": [0.5, -0.5]}
							}
						},
						{
							"origin": [-0.08702, -1.375, 4.875],
							"size": [0.16568, 0.1, 0.1],
							"uv": {
								"north": {"uv": [33, 43], "uv_size": [0.5, 0.5]},
								"east": {"uv": [43, 33], "uv_size": [0.5, 0.5]},
								"south": {"uv": [34, 43], "uv_size": [0.5, 0.5]},
								"west": {"uv": [43, 34], "uv_size": [0.5, 0.5]},
								"up": {"uv": [35, 43], "uv_size": [0.5, 0.5]},
								"down": {"uv": [43, 35.5], "uv_size": [0.5, -0.5]}
							}
						},
						{
							"origin": [0.09581, -1.55784, 4.876],
							"size": [0.1, 0.16568, 0.098],
							"pivot": [-0.00418, -1.475, 4.925],
							"rotation": [0, 0, 45],
							"uv": {
								"north": {"uv": [36, 43], "uv_size": [0.5, 0.5]},
								"east": {"uv": [43, 36], "uv_size": [0.5, 0.5]},
								"south": {"uv": [37, 43], "uv_size": [0.5, 0.5]},
								"west": {"uv": [43, 37], "uv_size": [0.5, 0.5]},
								"up": {"uv": [38, 43], "uv_size": [0.5, 0.5]},
								"down": {"uv": [43, 38.5], "uv_size": [0.5, -0.5]}
							}
						},
						{
							"origin": [0.09581, -1.68284, 4.875],
							"size": [0.1, 0.29068, 0.1],
							"uv": {
								"north": {"uv": [39, 43], "uv_size": [0.5, 0.5]},
								"east": {"uv": [43, 39], "uv_size": [0.5, 0.5]},
								"south": {"uv": [40, 43], "uv_size": [0.5, 0.5]},
								"west": {"uv": [43, 40], "uv_size": [0.5, 0.5]},
								"up": {"uv": [41, 43], "uv_size": [0.5, 0.5]},
								"down": {"uv": [43, 41.5], "uv_size": [0.5, -0.5]}
							}
						},
						{
							"origin": [-0.20418, -1.55784, 4.876],
							"size": [0.1, 0.16568, 0.098],
							"pivot": [-0.00418, -1.475, 4.925],
							"rotation": [0, 0, 45],
							"uv": {
								"north": {"uv": [42, 43], "uv_size": [0.5, 0.5]},
								"east": {"uv": [43, 42], "uv_size": [0.5, 0.5]},
								"south": {"uv": [43, 43], "uv_size": [0.5, 0.5]},
								"west": {"uv": [0, 44], "uv_size": [0.5, 0.5]},
								"up": {"uv": [44, 0], "uv_size": [0.5, 0.5]},
								"down": {"uv": [1, 44.5], "uv_size": [0.5, -0.5]}
							}
						},
						{
							"origin": [-0.20418, -1.68284, 4.875],
							"size": [0.1, 0.29068, 0.1],
							"uv": {
								"north": {"uv": [44, 1], "uv_size": [0.5, 0.5]},
								"east": {"uv": [2, 44], "uv_size": [0.5, 0.5]},
								"south": {"uv": [44, 2], "uv_size": [0.5, 0.5]},
								"west": {"uv": [3, 44], "uv_size": [0.5, 0.5]},
								"up": {"uv": [44, 3], "uv_size": [0.5, 0.5]},
								"down": {"uv": [4, 44.5], "uv_size": [0.5, -0.5]}
							}
						}
					]
				},
				{
					"name": "Bolt",
					"parent": "body",
					"pivot": [0, -5.35, -3.05],
					"cubes": [
						{
							"origin": [-0.75, -5.46228, -4.67926],
							"size": [1.5, 1.5, 4.5],
							"uv": {
								"north": {"uv": [30, 34], "uv_size": [1.5, 1.5]},
								"east": {"uv": [21, 13], "uv_size": [4.5, 1.5]},
								"south": {"uv": [32, 34], "uv_size": [1.5, 1.5]},
								"west": {"uv": [2, 22], "uv_size": [4.5, 1.5]},
								"up": {"uv": [14, 22], "uv_size": [1.5, 4.5]},
								"down": {"uv": [18, 26.5], "uv_size": [1.5, -4.5]}
							}
						},
						{
							"origin": [-0.75, -5.96228, -2.17926],
							"size": [1.5, 0.5, 2],
							"uv": {
								"north": {"uv": [41, 35], "uv_size": [1.5, 0.5]},
								"east": {"uv": [22, 39], "uv_size": [2, 0.5]},
								"south": {"uv": [36, 41], "uv_size": [1.5, 0.5]},
								"west": {"uv": [39, 23], "uv_size": [2, 0.5]},
								"up": {"uv": [31, 10], "uv_size": [1.5, 2]},
								"down": {"uv": [31, 14], "uv_size": [1.5, -2]}
							}
						}
					]
				},
				{
					"name": "vertical_grip",
					"parent": "Bolt",
					"pivot": [0, 0.25, 0.4],
					"cubes": [
						{
							"origin": [-0.68865, -6.145, -2.83875],
							"size": [1.35, 1.05, 1.53],
							"uv": {
								"north": {"uv": [37, 2], "uv_size": [1.5, 1]},
								"east": {"uv": [37, 3], "uv_size": [1.5, 1]},
								"south": {"uv": [37, 4], "uv_size": [1.5, 1]},
								"west": {"uv": [37, 5], "uv_size": [1.5, 1]},
								"up": {"uv": [0, 32], "uv_size": [1.5, 1.5]},
								"down": {"uv": [4, 33.5], "uv_size": [1.5, -1.5]}
							}
						},
						{
							"origin": [-0.57616, -5.545, -2.32125],
							"size": [1.125, 0.9, 0.495],
							"uv": {
								"north": {"uv": [20, 4], "uv_size": [1, 1]},
								"east": {"uv": [42, 9], "uv_size": [0.5, 1]},
								"south": {"uv": [33, 29], "uv_size": [1, 1]},
								"west": {"uv": [10, 42], "uv_size": [0.5, 1]},
								"up": {"uv": [42, 10], "uv_size": [1, 0.5]},
								"down": {"uv": [42, 11.5], "uv_size": [1, -0.5]}
							}
						},
						{
							"origin": [-0.46365, -8.1775, -2.52625],
							"size": [0.9, 2, 0.9],
							"pivot": [-0.01366, -7.79, -2.07625],
							"rotation": [0, -45, 0],
							"uv": {
								"north": {"uv": [36, 2], "uv_size": [1, 2]},
								"east": {"uv": [3, 36], "uv_size": [1, 2]},
								"south": {"uv": [4, 36], "uv_size": [1, 2]},
								"west": {"uv": [5, 36], "uv_size": [1, 2]},
								"up": {"uv": [34, 31], "uv_size": [1, 1]},
								"down": {"uv": [35, 24], "uv_size": [1, -1]}
							}
						},
						{
							"origin": [-0.55365, -8.5275, -2.61625],
							"size": [1.08, 0.45, 1.08],
							"pivot": [-0.01366, -7.69, -2.07625],
							"rotation": [0, -45, 0],
							"uv": {
								"north": {"uv": [13, 42], "uv_size": [1, 0.5]},
								"east": {"uv": [15, 42], "uv_size": [1, 0.5]},
								"south": {"uv": [16, 42], "uv_size": [1, 0.5]},
								"west": {"uv": [42, 16], "uv_size": [1, 0.5]},
								"up": {"uv": [35, 26], "uv_size": [1, 1]},
								"down": {"uv": [38, 21], "uv_size": [1, -1]}
							}
						}
					]
				},
				{
					"name": "light_grip",
					"parent": "Bolt",
					"pivot": [0, 0.55, -0.6],
					"cubes": [
						{
							"origin": [-0.88866, -6, -4.25],
							"size": [1.75, 0.5, 3.2],
							"uv": {
								"north": {"uv": [38, 21], "uv_size": [2, 0.5]},
								"east": {"uv": [37, 6], "uv_size": [3, 0.5]},
								"south": {"uv": [38, 22], "uv_size": [2, 0.5]},
								"west": {"uv": [37, 7], "uv_size": [3, 0.5]},
								"up": {"uv": [23, 7], "uv_size": [2, 3]},
								"down": {"uv": [24, 3], "uv_size": [2, -3]}
							}
						},
						{
							"origin": [-0.76366, -6.4, -4.175],
							"size": [1.5, 0.5, 3],
							"uv": {
								"north": {"uv": [34, 39], "uv_size": [1.5, 0.5]},
								"east": {"uv": [37, 8], "uv_size": [3, 0.5]},
								"south": {"uv": [39, 35], "uv_size": [1.5, 0.5]},
								"west": {"uv": [37, 9], "uv_size": [3, 0.5]},
								"up": {"uv": [0, 25], "uv_size": [1.5, 3]},
								"down": {"uv": [26, 17], "uv_size": [1.5, -3]}
							}
						}
					]
				},
				{
					"name": "grips",
					"parent": "gun_body",
					"pivot": [0.21213, -3.05233, -8.94767]
				},
				{
					"name": "iron_bayonet",
					"parent": "grips",
					"pivot": [0, 0.25, -0.4],
					"cubes": [
						{
							"origin": [-0.57829, -3.86464, -11.45],
							"size": [1.35, 1.35, 0.55],
							"pivot": [-0.0283, -3.06464, -11.1625],
							"rotation": [0, 0, 45],
							"uv": {
								"north": {"uv": [8, 32], "uv_size": [1.5, 1.5]},
								"east": {"uv": [36, 39], "uv_size": [0.5, 1.5]},
								"south": {"uv": [14, 32], "uv_size": [1.5, 1.5]},
								"west": {"uv": [39, 36], "uv_size": [0.5, 1.5]},
								"up": {"uv": [37, 39], "uv_size": [1.5, 0.5]},
								"down": {"uv": [39, 38.5], "uv_size": [1.5, -0.5]}
							}
						},
						{
							"origin": [-0.76366, -4.725, -11.425],
							"size": [1.5, 1.5, 0.5],
							"uv": {
								"north": {"uv": [32, 14], "uv_size": [1.5, 1.5]},
								"east": {"uv": [39, 39], "uv_size": [0.5, 1.5]},
								"south": {"uv": [19, 32], "uv_size": [1.5, 1.5]},
								"west": {"uv": [0, 40], "uv_size": [0.5, 1.5]},
								"up": {"uv": [40, 0], "uv_size": [1.5, 0.5]},
								"down": {"uv": [1, 40.5], "uv_size": [1.5, -0.5]}
							}
						},
						{
							"origin": [-0.38866, -5.725, -11.425],
							"size": [0.75, 1, 0.5],
							"uv": {
								"north": {"uv": [22, 38], "uv_size": [1, 1]},
								"east": {"uv": [17, 42], "uv_size": [0.5, 1]},
								"south": {"uv": [38, 23], "uv_size": [1, 1]},
								"west": {"uv": [42, 17], "uv_size": [0.5, 1]},
								"up": {"uv": [42, 18], "uv_size": [1, 0.5]},
								"down": {"uv": [42, 19.5], "uv_size": [1, -0.5]}
							}
						},
						{
							"origin": [-0.01366, -6.3, -20.675],
							"size": [0, 1.55, 10.25],
							"uv": {
								"north": {"uv": [0, 0], "uv_size": [0, 1.5]},
								"east": {"uv": [0, 0], "uv_size": [10.5, 1.5]},
								"south": {"uv": [0, 0], "uv_size": [0, 1.5]},
								"up": {"uv": [0, 0], "uv_size": [0, 10.5]},
								"down": {"uv": [0, 10.5], "uv_size": [0, -10.5]}
							}
						}
					]
				},
				{
					"name": "anthralite_bayonet",
					"parent": "grips",
					"pivot": [0, 0.25, -0.4],
					"cubes": [
						{
							"origin": [-0.56883, -3.86464, -11.45],
							"size": [1.35, 1.35, 0.55],
							"pivot": [-0.01882, -3.06464, -11.1625],
							"rotation": [0, 0, 45],
							"uv": {
								"north": {"uv": [32, 19], "uv_size": [1.5, 1.5]},
								"east": {"uv": [40, 1], "uv_size": [0.5, 1.5]},
								"south": {"uv": [32, 24], "uv_size": [1.5, 1.5]},
								"west": {"uv": [3, 40], "uv_size": [0.5, 1.5]},
								"up": {"uv": [40, 3], "uv_size": [1.5, 0.5]},
								"down": {"uv": [4, 40.5], "uv_size": [1.5, -0.5]}
							}
						},
						{
							"origin": [-0.75418, -4.725, -11.425],
							"size": [1.5, 1.5, 0.5],
							"uv": {
								"north": {"uv": [27, 32], "uv_size": [1.5, 1.5]},
								"east": {"uv": [40, 4], "uv_size": [0.5, 1.5]},
								"south": {"uv": [29, 32], "uv_size": [1.5, 1.5]},
								"west": {"uv": [40, 6], "uv_size": [0.5, 1.5]},
								"up": {"uv": [8, 40], "uv_size": [1.5, 0.5]},
								"down": {"uv": [40, 8.5], "uv_size": [1.5, -0.5]}
							}
						},
						{
							"origin": [-0.37918, -5.725, -11.425],
							"size": [0.75, 1, 0.5],
							"uv": {
								"north": {"uv": [24, 38], "uv_size": [1, 1]},
								"east": {"uv": [20, 42], "uv_size": [0.5, 1]},
								"south": {"uv": [38, 24], "uv_size": [1, 1]},
								"west": {"uv": [21, 42], "uv_size": [0.5, 1]},
								"up": {"uv": [22, 42], "uv_size": [1, 0.5]},
								"down": {"uv": [42, 22.5], "uv_size": [1, -0.5]}
							}
						},
						{
							"origin": [-0.10418, -6.3, -20.675],
							"size": [0, 1.55, 10.25],
							"uv": {
								"north": {"uv": [0, 0], "uv_size": [0, 1.5]},
								"east": {"uv": [0, 2], "uv_size": [10.5, 1.5]},
								"south": {"uv": [0, 0], "uv_size": [0, 1.5]},
								"up": {"uv": [0, 0], "uv_size": [0, 10.5]},
								"down": {"uv": [0, 10.5], "uv_size": [0, -10.5]}
							}
						}
					]
				},
				{
					"name": "netherite_bayonet",
					"parent": "grips",
					"pivot": [0, 0.25, -0.4],
					"cubes": [
						{
							"origin": [-0.57829, -3.86464, -11.45],
							"size": [1.35, 1.35, 0.55],
							"pivot": [-0.0283, -3.06464, -11.1625],
							"rotation": [0, 0, 45],
							"uv": {
								"north": {"uv": [31, 32], "uv_size": [1.5, 1.5]},
								"east": {"uv": [40, 9], "uv_size": [0.5, 1.5]},
								"south": {"uv": [33, 4], "uv_size": [1.5, 1.5]},
								"west": {"uv": [10, 40], "uv_size": [0.5, 1.5]},
								"up": {"uv": [11, 40], "uv_size": [1.5, 0.5]},
								"down": {"uv": [40, 11.5], "uv_size": [1.5, -0.5]}
							}
						},
						{
							"origin": [-0.76366, -4.725, -11.425],
							"size": [1.5, 1.5, 0.5],
							"uv": {
								"north": {"uv": [6, 33], "uv_size": [1.5, 1.5]},
								"east": {"uv": [40, 12], "uv_size": [0.5, 1.5]},
								"south": {"uv": [33, 6], "uv_size": [1.5, 1.5]},
								"west": {"uv": [13, 40], "uv_size": [0.5, 1.5]},
								"up": {"uv": [14, 40], "uv_size": [1.5, 0.5]},
								"down": {"uv": [40, 16.5], "uv_size": [1.5, -0.5]}
							}
						},
						{
							"origin": [-0.38866, -5.725, -11.425],
							"size": [0.75, 1, 0.5],
							"uv": {
								"north": {"uv": [38, 25], "uv_size": [1, 1]},
								"east": {"uv": [23, 42], "uv_size": [0.5, 1]},
								"south": {"uv": [26, 38], "uv_size": [1, 1]},
								"west": {"uv": [24, 42], "uv_size": [0.5, 1]},
								"up": {"uv": [42, 24], "uv_size": [1, 0.5]},
								"down": {"uv": [25, 42.5], "uv_size": [1, -0.5]}
							}
						},
						{
							"origin": [-0.01366, -6.3, -20.675],
							"size": [0, 1.55, 10.25],
							"uv": {
								"north": {"uv": [0, 0], "uv_size": [0, 1.5]},
								"east": {"uv": [0, 4], "uv_size": [10.5, 1.5]},
								"south": {"uv": [0, 0], "uv_size": [0, 1.5]},
								"up": {"uv": [0, 0], "uv_size": [0, 10.5]},
								"down": {"uv": [0, 10.5], "uv_size": [0, -10.5]}
							}
						}
					]
				},
				{
					"name": "diamond_bayonet",
					"parent": "grips",
					"pivot": [0, 0.25, -0.4],
					"cubes": [
						{
							"origin": [-0.57829, -3.86464, -11.475],
							"size": [1.35, 1.35, 0.55],
							"pivot": [-0.0283, -3.06464, -11.1875],
							"rotation": [0, 0, 45],
							"uv": {
								"north": {"uv": [33, 10], "uv_size": [1.5, 1.5]},
								"east": {"uv": [17, 40], "uv_size": [0.5, 1.5]},
								"south": {"uv": [33, 12], "uv_size": [1.5, 1.5]},
								"west": {"uv": [40, 17], "uv_size": [0.5, 1.5]},
								"up": {"uv": [18, 40], "uv_size": [1.5, 0.5]},
								"down": {"uv": [40, 19.5], "uv_size": [1.5, -0.5]}
							}
						},
						{
							"origin": [-0.76366, -4.725, -11.45],
							"size": [1.5, 1.5, 0.5],
							"uv": {
								"north": {"uv": [33, 32], "uv_size": [1.5, 1.5]},
								"east": {"uv": [20, 40], "uv_size": [0.5, 1.5]},
								"south": {"uv": [0, 34], "uv_size": [1.5, 1.5]},
								"west": {"uv": [40, 20], "uv_size": [0.5, 1.5]},
								"up": {"uv": [21, 40], "uv_size": [1.5, 0.5]},
								"down": {"uv": [40, 22.5], "uv_size": [1.5, -0.5]}
							}
						},
						{
							"origin": [-0.38866, -5.725, -11.45],
							"size": [0.75, 1, 0.5],
							"uv": {
								"north": {"uv": [38, 26], "uv_size": [1, 1]},
								"east": {"uv": [42, 25], "uv_size": [0.5, 1]},
								"south": {"uv": [27, 38], "uv_size": [1, 1]},
								"west": {"uv": [26, 42], "uv_size": [0.5, 1]},
								"up": {"uv": [42, 26], "uv_size": [1, 0.5]},
								"down": {"uv": [27, 42.5], "uv_size": [1, -0.5]}
							}
						},
						{
							"origin": [-0.01366, -6.3, -20.7],
							"size": [0, 1.55, 10.25],
							"uv": {
								"north": {"uv": [0, 0], "uv_size": [0, 1.5]},
								"east": {"uv": [0, 6], "uv_size": [10.5, 1.5]},
								"south": {"uv": [0, 0], "uv_size": [0, 1.5]},
								"up": {"uv": [0, 0], "uv_size": [0, 10.5]},
								"down": {"uv": [0, 10.5], "uv_size": [0, -10.5]}
							}
						}
					]
				},
				{
					"name": "barrels",
					"parent": "gun_body",
					"pivot": [0, -5.35, 0.2]
				},
				{
					"name": "standard_barrel",
					"parent": "barrels",
					"pivot": [0.21213, -3.05233, -8.94767],
					"cubes": [
						{
							"origin": [-0.43787, -3.64852, -11.44642],
							"size": [1, 1, 4.5],
							"pivot": [0.21214, -3.29852, -11.69642],
							"rotation": [0, 0, -45],
							"uv": {
								"north": {"uv": [38, 27], "uv_size": [1, 1]},
								"east": {"uv": [24, 23], "uv_size": [4.5, 1]},
								"south": {"uv": [28, 38], "uv_size": [1, 1]},
								"west": {"uv": [25, 9], "uv_size": [4.5, 1]},
								"up": {"uv": [6, 24], "uv_size": [1, 4.5]},
								"down": {"uv": [13, 29.5], "uv_size": [1, -4.5]}
							}
						},
						{
							"origin": [-0.73535, -4.01316, -11.94642],
							"size": [1.5, 1.5, 0.5],
							"pivot": [-0.03536, -3.26316, -3.60892],
							"rotation": [0, 0, 45],
							"uv": {
								"north": {"uv": [34, 34], "uv_size": [1.5, 1.5]},
								"east": {"uv": [41, 36], "uv_size": [0.5, 1.5]},
								"south": {"uv": [35, 4], "uv_size": [1.5, 1.5]},
								"west": {"uv": [38, 41], "uv_size": [0.5, 1.5]},
								"up": {"uv": [41, 38], "uv_size": [1.5, 0.5]},
								"down": {"uv": [39, 41.5], "uv_size": [1.5, -0.5]}
							}
						}
					]
				},
				{
					"name": "extended_barrel",
					"parent": "barrels",
					"pivot": [-0.00189, -2.75233, -13.94767],
					"cubes": [
						{
							"origin": [-0.43787, -3.64852, -16.44642],
							"size": [1, 1, 8],
							"pivot": [0.21214, -3.29852, -16.69642],
							"rotation": [0, 0, -45],
							"uv": {
								"north": {"uv": [24, 39], "uv_size": [1, 1]},
								"east": {"uv": [13, 5], "uv_size": [8, 1]},
								"south": {"uv": [39, 24], "uv_size": [1, 1]},
								"west": {"uv": [16, 12], "uv_size": [8, 1]},
								"up": {"uv": [0, 17], "uv_size": [1, 8]},
								"down": {"uv": [1, 25], "uv_size": [1, -8]}
							}
						},
						{
							"origin": [-0.73535, -4.01316, -16.94642],
							"size": [1.5, 1.5, 0.5],
							"pivot": [-0.03536, -3.26316, -8.60892],
							"rotation": [0, 0, 45],
							"uv": {
								"north": {"uv": [6, 35], "uv_size": [1.5, 1.5]},
								"east": {"uv": [0, 42], "uv_size": [0.5, 1.5]},
								"south": {"uv": [35, 6], "uv_size": [1.5, 1.5]},
								"west": {"uv": [42, 1], "uv_size": [0.5, 1.5]},
								"up": {"uv": [42, 3], "uv_size": [1.5, 0.5]},
								"down": {"uv": [5, 42.5], "uv_size": [1.5, -0.5]}
							}
						},
						{
							"origin": [-0.73535, -4.01316, -8.47142],
							"size": [1.5, 1.5, 1.5],
							"pivot": [-0.03536, -3.26316, 0.86608],
							"rotation": [0, 0, 45],
							"uv": {
								"north": {"uv": [10, 35], "uv_size": [1.5, 1.5]},
								"east": {"uv": [35, 10], "uv_size": [1.5, 1.5]},
								"south": {"uv": [35, 12], "uv_size": [1.5, 1.5]},
								"west": {"uv": [35, 31], "uv_size": [1.5, 1.5]},
								"up": {"uv": [0, 36], "uv_size": [1.5, 1.5]},
								"down": {"uv": [36, 1.5], "uv_size": [1.5, -1.5]}
							}
						}
					]
				},
				{
					"name": "muzzle_brake",
					"parent": "barrels",
					"pivot": [-0.42897, -4.225, -3.8],
					"cubes": [
						{
							"origin": [-0.69891, -3.88898, -14.97075],
							"size": [1.274, 1.274, 0.52325],
							"pivot": [-0.06191, -3.32023, -14.73662],
							"rotation": [0, 0, 45],
							"uv": {
								"north": {"uv": [2, 34], "uv_size": [1.5, 1.5]},
								"east": {"uv": [23, 40], "uv_size": [0.5, 1.5]},
								"south": {"uv": [4, 34], "uv_size": [1.5, 1.5]},
								"west": {"uv": [24, 40], "uv_size": [0.5, 1.5]},
								"up": {"uv": [40, 24], "uv_size": [1.5, 0.5]},
								"down": {"uv": [25, 40.5], "uv_size": [1.5, -0.5]}
							}
						},
						{
							"origin": [-0.92642, -4.11648, -12.4275],
							"size": [1.729, 1.729, 0.52325],
							"pivot": [-0.06191, -3.32023, -14.21338],
							"rotation": [0, 0, 45],
							"uv": {
								"north": {"uv": [8, 34], "uv_size": [1.5, 1.5]},
								"east": {"uv": [40, 26], "uv_size": [0.5, 1.5]},
								"south": {"uv": [14, 34], "uv_size": [1.5, 1.5]},
								"west": {"uv": [27, 40], "uv_size": [0.5, 1.5]},
								"up": {"uv": [40, 28], "uv_size": [1.5, 0.5]},
								"down": {"uv": [40, 29.5], "uv_size": [1.5, -0.5]}
							}
						},
						{
							"origin": [-0.92642, -4.11648, -13.92425],
							"size": [0.58, 0, 1.49675],
							"pivot": [-0.06191, -3.32023, -14.73663],
							"rotation": [0, 0, 45],
							"uv": {
								"north": {"uv": [0, 0], "uv_size": [0.5, 0]},
								"east": {"uv": [0, 0], "uv_size": [1.5, 0]},
								"south": {"uv": [0, 0], "uv_size": [0.5, 0]},
								"west": {"uv": [0, 0], "uv_size": [1.5, 0]},
								"up": {"uv": [30, 40], "uv_size": [0.5, 1.5]},
								"down": {"uv": [31, 41.5], "uv_size": [0.5, -1.5]}
							}
						},
						{
							"origin": [-0.92642, -4.11648, -13.92425],
							"size": [0, 0.58, 1.49675],
							"pivot": [-0.06191, -3.32023, -14.73663],
							"rotation": [0, 0, 45],
							"uv": {
								"north": {"uv": [0, 0], "uv_size": [0, 0.5]},
								"east": {"uv": [40, 33], "uv_size": [1.5, 0.5]},
								"south": {"uv": [0, 0], "uv_size": [0, 0.5]},
								"west": {"uv": [34, 40], "uv_size": [1.5, 0.5]},
								"up": {"uv": [0, 0], "uv_size": [0, 1.5]},
								"down": {"uv": [0, 1.5], "uv_size": [0, -1.5]}
							}
						},
						{
							"origin": [0.31911, -4.11648, -13.92425],
							"size": [0.58, 0, 1.49675],
							"pivot": [0.0346, -3.32023, -14.73663],
							"rotation": [0, 0, -45],
							"uv": {
								"north": {"uv": [0, 0], "uv_size": [0.5, 0]},
								"east": {"uv": [0, 0], "uv_size": [1.5, 0]},
								"south": {"uv": [0, 0], "uv_size": [0.5, 0]},
								"west": {"uv": [0, 0], "uv_size": [1.5, 0]},
								"up": {"uv": [32, 40], "uv_size": [0.5, 1.5]},
								"down": {"uv": [40, 37.5], "uv_size": [0.5, -1.5]}
							}
						},
						{
							"origin": [0.89911, -4.11648, -13.92425],
							"size": [0, 0.58, 1.49675],
							"pivot": [0.0346, -3.32023, -14.73663],
							"rotation": [0, 0, -45],
							"uv": {
								"north": {"uv": [0, 0], "uv_size": [0, 0.5]},
								"east": {"uv": [40, 34], "uv_size": [1.5, 0.5]},
								"south": {"uv": [0, 0], "uv_size": [0, 0.5]},
								"west": {"uv": [37, 40], "uv_size": [1.5, 0.5]},
								"up": {"uv": [0, 0], "uv_size": [0, 1.5]},
								"down": {"uv": [0, 1.5], "uv_size": [0, -1.5]}
							}
						},
						{
							"origin": [-0.87816, -4.13647, -13.92425],
							"size": [0, 0.58, 1.49675],
							"pivot": [-0.01366, -3.27197, -13.07588],
							"rotation": [0, 0, -45],
							"uv": {
								"north": {"uv": [0, 0], "uv_size": [0, 0.5]},
								"east": {"uv": [40, 39], "uv_size": [1.5, 0.5]},
								"south": {"uv": [0, 0], "uv_size": [0, 0.5]},
								"west": {"uv": [40, 40], "uv_size": [1.5, 0.5]},
								"up": {"uv": [0, 0], "uv_size": [0, 1.5]},
								"down": {"uv": [0, 1.5], "uv_size": [0, -1.5]}
							}
						},
						{
							"origin": [-0.87816, -4.13647, -13.92425],
							"size": [0.58, 0, 1.49675],
							"pivot": [-0.01366, -3.27197, -13.07588],
							"rotation": [0, 0, -45],
							"uv": {
								"north": {"uv": [0, 0], "uv_size": [0.5, 0]},
								"east": {"uv": [0, 0], "uv_size": [1.5, 0]},
								"south": {"uv": [0, 0], "uv_size": [0.5, 0]},
								"west": {"uv": [0, 0], "uv_size": [1.5, 0]},
								"up": {"uv": [1, 41], "uv_size": [0.5, 1.5]},
								"down": {"uv": [41, 2.5], "uv_size": [0.5, -1.5]}
							}
						},
						{
							"origin": [0.27085, -2.40747, -13.92425],
							"size": [0.58, 0, 1.49675],
							"pivot": [-0.01366, -3.27197, -13.07588],
							"rotation": [0, 0, -45],
							"uv": {
								"north": {"uv": [0, 0], "uv_size": [0.5, 0]},
								"east": {"uv": [0, 0], "uv_size": [1.5, 0]},
								"south": {"uv": [0, 0], "uv_size": [0.5, 0]},
								"west": {"uv": [0, 0], "uv_size": [1.5, 0]},
								"up": {"uv": [2, 41], "uv_size": [0.5, 1.5]},
								"down": {"uv": [4, 42.5], "uv_size": [0.5, -1.5]}
							}
						},
						{
							"origin": [0.85084, -2.98747, -13.92425],
							"size": [0, 0.58, 1.49675],
							"pivot": [-0.01366, -3.27197, -13.07588],
							"rotation": [0, 0, -45],
							"uv": {
								"north": {"uv": [0, 0], "uv_size": [0, 0.5]},
								"east": {"uv": [41, 4], "uv_size": [1.5, 0.5]},
								"south": {"uv": [0, 0], "uv_size": [0, 0.5]},
								"west": {"uv": [5, 41], "uv_size": [1.5, 0.5]},
								"up": {"uv": [0, 0], "uv_size": [0, 1.5]},
								"down": {"uv": [0, 1.5], "uv_size": [0, -1.5]}
							}
						},
						{
							"origin": [-0.92642, -4.11648, -14.4475],
							"size": [1.729, 1.729, 0.52325],
							"pivot": [-0.06191, -3.32023, -14.21338],
							"rotation": [0, 0, 45],
							"uv": {
								"north": {"uv": [34, 14], "uv_size": [1.5, 1.5]},
								"east": {"uv": [41, 5], "uv_size": [0.5, 1.5]},
								"south": {"uv": [16, 34], "uv_size": [1.5, 1.5]},
								"west": {"uv": [7, 41], "uv_size": [0.5, 1.5]},
								"up": {"uv": [41, 7], "uv_size": [1.5, 0.5]},
								"down": {"uv": [8, 41.5], "uv_size": [1.5, -0.5]}
							}
						}
					]
				},
				{
					"name": "advanced_silencer",
					"parent": "barrels",
					"pivot": [-0.02904, -4.125, 3.275],
					"cubes": [
						{
							"origin": [-0.85722, -4.05, -17.0125],
							"size": [1.5, 1.5, 4.575],
							"pivot": [-0.05721, -3.425, -15.5],
							"rotation": [0, 0, 45],
							"uv": {
								"north": {"uv": [34, 17], "uv_size": [1.5, 1.5]},
								"east": {"uv": [18, 6], "uv_size": [4.5, 1.5]},
								"south": {"uv": [19, 34], "uv_size": [1.5, 1.5]},
								"west": {"uv": [19, 15], "uv_size": [4.5, 1.5]},
								"up": {"uv": [16, 19], "uv_size": [1.5, 4.5]},
								"down": {"uv": [19, 21.5], "uv_size": [1.5, -4.5]}
							}
						},
						{
							"origin": [-0.68399, -3.7, -12.4375],
							"size": [1.15, 1.15, 0.5],
							"pivot": [-0.234, -3.325, -15],
							"rotation": [0, 0, 45],
							"uv": {
								"north": {"uv": [38, 28], "uv_size": [1, 1]},
								"east": {"uv": [28, 42], "uv_size": [0.5, 1]},
								"south": {"uv": [29, 38], "uv_size": [1, 1]},
								"west": {"uv": [42, 28], "uv_size": [0.5, 1]},
								"up": {"uv": [29, 42], "uv_size": [1, 0.5]},
								"down": {"uv": [42, 29.5], "uv_size": [1, -0.5]}
							}
						}
					]
				},
				{
					"name": "silencer",
					"parent": "barrels",
					"pivot": [-0.23345, 3.03, -4.325],
					"cubes": [
						{
							"origin": [-0.75722, -3.9, -16.0875],
							"size": [1.4, 1.4, 0.575],
							"pivot": [-0.05721, -3.275, -15.05],
							"rotation": [0, 0, 45],
							"uv": {
								"north": {"uv": [34, 19], "uv_size": [1.5, 1.5]},
								"east": {"uv": [41, 9], "uv_size": [0.5, 1.5]},
								"south": {"uv": [21, 34], "uv_size": [1.5, 1.5]},
								"west": {"uv": [11, 41], "uv_size": [0.5, 1.5]},
								"up": {"uv": [41, 12], "uv_size": [1.5, 0.5]},
								"down": {"uv": [41, 13.5], "uv_size": [1.5, -0.5]}
							}
						},
						{
							"origin": [-1.00722, -4.15, -15.5125],
							"size": [1.9, 1.9, 3.575],
							"pivot": [-0.05721, -3.275, -14.475],
							"rotation": [0, 0, 45],
							"uv": {
								"north": {"uv": [25, 27], "uv_size": [2, 2]},
								"east": {"uv": [17, 2], "uv_size": [3.5, 2]},
								"south": {"uv": [27, 27], "uv_size": [2, 2]},
								"west": {"uv": [17, 13], "uv_size": [3.5, 2]},
								"up": {"uv": [17, 15], "uv_size": [2, 3.5]},
								"down": {"uv": [6, 21.5], "uv_size": [2, -3.5]}
							}
						},
						{
							"origin": [1.34278, -5.125, -13.9625],
							"size": [0, 1.9, 0.5],
							"uv": {
								"north": {"uv": [0, 0], "uv_size": [0, 2]},
								"east": {"uv": [38, 29], "uv_size": [0.5, 2]},
								"south": {"uv": [0, 0], "uv_size": [0, 2]},
								"west": {"uv": [30, 38], "uv_size": [0.5, 2]},
								"up": {"uv": [0, 0], "uv_size": [0, 0.5]},
								"down": {"uv": [0, 0.5], "uv_size": [0, -0.5]}
							}
						},
						{
							"origin": [-1.33221, -4.625, -14.4875],
							"size": [0, 1.4, 0.5],
							"uv": {
								"north": {"uv": [0, 0], "uv_size": [0, 1.5]},
								"east": {"uv": [12, 41], "uv_size": [0.5, 1.5]},
								"south": {"uv": [0, 0], "uv_size": [0, 1.5]},
								"west": {"uv": [14, 41], "uv_size": [0.5, 1.5]},
								"up": {"uv": [0, 0], "uv_size": [0, 0.5]},
								"down": {"uv": [0, 0.5], "uv_size": [0, -0.5]}
							}
						}
					]
				},
				{
					"name": "stocks",
					"parent": "gun_body",
					"pivot": [0, -5.35, 0.2]
				},
				{
					"name": "standard_grip",
					"parent": "stocks",
					"pivot": [0.00582, -8.35781, 6.00249],
					"cubes": [
						{
							"origin": [-0.49419, -7.38281, 5.05249],
							"size": [1, 1.75, 1.5],
							"pivot": [-0.04418, -7.73281, 5.00249],
							"rotation": [22.5, 0, 0],
							"uv": {
								"north": {"uv": [8, 36], "uv_size": [1, 2]},
								"east": {"uv": [29, 27], "uv_size": [1.5, 2]},
								"south": {"uv": [36, 8], "uv_size": [1, 2]},
								"west": {"uv": [4, 30], "uv_size": [1.5, 2]},
								"up": {"uv": [6, 37], "uv_size": [1, 1.5]},
								"down": {"uv": [7, 38.5], "uv_size": [1, -1.5]}
							}
						},
						{
							"origin": [-0.24419, -7.63281, 5.05249],
							"size": [0.5, 0.25, 1.5],
							"pivot": [-0.04418, -7.73281, 5.00249],
							"rotation": [22.5, 0, 0],
							"uv": {
								"north": {"uv": [44, 4], "uv_size": [0.5, 0.5]},
								"east": {"uv": [41, 14], "uv_size": [1.5, 0.5]},
								"south": {"uv": [5, 44], "uv_size": [0.5, 0.5]},
								"west": {"uv": [15, 41], "uv_size": [1.5, 0.5]},
								"up": {"uv": [41, 17], "uv_size": [0.5, 1.5]},
								"down": {"uv": [18, 42.5], "uv_size": [0.5, -1.5]}
							}
						}
					]
				},
				{
					"name": "weighted_stock",
					"parent": "stocks",
					"pivot": [0, -0.75, -0.2],
					"cubes": [
						{
							"origin": [-0.66517, -7.73974, 9.49556],
							"size": [1.3125, 2.25, 3.75],
							"uv": {
								"north": {"uv": [28, 14], "uv_size": [1.5, 2.5]},
								"east": {"uv": [2, 13], "uv_size": [4, 2.5]},
								"south": {"uv": [16, 28], "uv_size": [1.5, 2.5]},
								"west": {"uv": [13, 2], "uv_size": [4, 2.5]},
								"up": {"uv": [2, 24], "uv_size": [1.5, 4]},
								"down": {"uv": [24, 7], "uv_size": [1.5, -4]}
							}
						},
						{
							"origin": [-0.5307, -5.88974, 7.19556],
							"size": [1.0625, 0.25, 6.5],
							"uv": {
								"north": {"uv": [30, 42], "uv_size": [1, 0.5]},
								"east": {"uv": [29, 0], "uv_size": [6.5, 0.5]},
								"south": {"uv": [42, 30], "uv_size": [1, 0.5]},
								"west": {"uv": [29, 1], "uv_size": [6.5, 0.5]},
								"up": {"uv": [7, 22], "uv_size": [1, 6.5]},
								"down": {"uv": [20, 28.5], "uv_size": [1, -6.5]}
							}
						},
						{
							"origin": [-0.5307, -7.56474, 7.19556],
							"size": [1.0625, 1.675, 6.5],
							"uv": {
								"north": {"uv": [10, 37], "uv_size": [1, 1.5]},
								"east": {"uv": [10, 14], "uv_size": [6.5, 1.5]},
								"south": {"uv": [37, 10], "uv_size": [1, 1.5]},
								"west": {"uv": [16, 8], "uv_size": [6.5, 1.5]},
								"up": {"uv": [21, 22], "uv_size": [1, 6.5]},
								"down": {"uv": [22, 28.5], "uv_size": [1, -6.5]}
							}
						},
						{
							"origin": [-0.49945, -9.75224, 13.69556],
							"size": [1, 3.8625, 0.5],
							"uv": {
								"north": {"uv": [12, 27], "uv_size": [1, 4]},
								"east": {"uv": [9, 36], "uv_size": [0.5, 4]},
								"south": {"uv": [0, 28], "uv_size": [1, 4]},
								"west": {"uv": [13, 36], "uv_size": [0.5, 4]},
								"up": {"uv": [31, 42], "uv_size": [1, 0.5]},
								"down": {"uv": [42, 31.5], "uv_size": [1, -0.5]}
							}
						},
						{
							"origin": [-0.52971, -8.98974, 11.18306],
							"size": [1.06051, 1.425, 2.5125],
							"uv": {
								"north": {"uv": [11, 37], "uv_size": [1, 1.5]},
								"east": {"uv": [28, 7], "uv_size": [2.5, 1.5]},
								"south": {"uv": [37, 12], "uv_size": [1, 1.5]},
								"west": {"uv": [28, 19], "uv_size": [2.5, 1.5]},
								"up": {"uv": [3, 31], "uv_size": [1, 2.5]},
								"down": {"uv": [12, 33.5], "uv_size": [1, -2.5]}
							}
						},
						{
							"origin": [-0.52971, -10.11474, 13.07681],
							"size": [1.06051, 1.125, 0.61875],
							"uv": {
								"north": {"uv": [31, 38], "uv_size": [1, 1]},
								"east": {"uv": [32, 42], "uv_size": [0.5, 1]},
								"south": {"uv": [38, 31], "uv_size": [1, 1]},
								"west": {"uv": [42, 33], "uv_size": [0.5, 1]},
								"up": {"uv": [34, 42], "uv_size": [1, 0.5]},
								"down": {"uv": [42, 34.5], "uv_size": [1, -0.5]}
							}
						},
						{
							"origin": [-0.53169, -7.93974, 7.03306],
							"size": [1.06449, 1.625, 6.825],
							"pivot": [0.15779, -7.05224, 8.03306],
							"rotation": [-22.5, 0, 0],
							"uv": {
								"north": {"uv": [37, 14], "uv_size": [1, 1.5]},
								"east": {"uv": [2, 11], "uv_size": [7, 1.5]},
								"south": {"uv": [37, 16], "uv_size": [1, 1.5]},
								"west": {"uv": [11, 6], "uv_size": [7, 1.5]},
								"up": {"uv": [10, 18], "uv_size": [1, 7]},
								"down": {"uv": [11, 25], "uv_size": [1, -7]}
							}
						},
						{
							"origin": [-0.51418, -7.53457, 6.92378],
							"size": [1.02, 1.85, 1],
							"uv": {
								"north": {"uv": [14, 36], "uv_size": [1, 2]},
								"east": {"uv": [36, 14], "uv_size": [1, 2]},
								"south": {"uv": [15, 36], "uv_size": [1, 2]},
								"west": {"uv": [16, 36], "uv_size": [1, 2]},
								"up": {"uv": [32, 38], "uv_size": [1, 1]},
								"down": {"uv": [38, 33], "uv_size": [1, -1]}
							}
						},
						{
							"origin": [-0.38918, -7.43457, 7.87378],
							"size": [0.77, 1.6, 1],
							"uv": {
								"north": {"uv": [37, 18], "uv_size": [1, 1.5]},
								"east": {"uv": [37, 20], "uv_size": [1, 1.5]},
								"south": {"uv": [37, 22], "uv_size": [1, 1.5]},
								"west": {"uv": [37, 24], "uv_size": [1, 1.5]},
								"up": {"uv": [38, 33], "uv_size": [1, 1]},
								"down": {"uv": [38, 35], "uv_size": [1, -1]}
							}
						},
						{
							"origin": [-0.50418, -7.5, 4.8],
							"size": [1, 1.85, 2.25],
							"pivot": [-0.05419, -7.2, 6.9],
							"rotation": [-22.5, 0, 0],
							"uv": {
								"north": {"uv": [36, 16], "uv_size": [1, 2]},
								"east": {"uv": [23, 24], "uv_size": [2.5, 2]},
								"south": {"uv": [17, 36], "uv_size": [1, 2]},
								"west": {"uv": [25, 7], "uv_size": [2.5, 2]},
								"up": {"uv": [17, 31], "uv_size": [1, 2.5]},
								"down": {"uv": [31, 21.5], "uv_size": [1, -2.5]}
							}
						},
						{
							"origin": [-0.49419, -7.38281, 5.80249],
							"size": [1, 1.75, 1.5],
							"pivot": [-0.04418, -7.73281, 5.00249],
							"rotation": [45, 0, 0],
							"uv": {
								"north": {"uv": [8, 36], "uv_size": [1, 2]},
								"east": {"uv": [29, 27], "uv_size": [1.5, 2]},
								"south": {"uv": [36, 8], "uv_size": [1, 2]},
								"west": {"uv": [4, 30], "uv_size": [1.5, 2]},
								"up": {"uv": [6, 37], "uv_size": [1, 1.5]},
								"down": {"uv": [7, 38.5], "uv_size": [1, -1.5]}
							}
						}
					]
				},
				{
					"name": "wooden_stock",
					"parent": "stocks",
					"pivot": [0, -0.75, 0.7],
					"cubes": [
						{
							"origin": [-0.53543, -5.88974, 7.09556],
							"size": [1.0625, 0.25, 6.5],
							"uv": {
								"north": {"uv": [35, 42], "uv_size": [1, 0.5]},
								"east": {"uv": [29, 2], "uv_size": [6.5, 0.5]},
								"south": {"uv": [36, 42], "uv_size": [1, 0.5]},
								"west": {"uv": [29, 3], "uv_size": [6.5, 0.5]},
								"up": {"uv": [23, 0], "uv_size": [1, 6.5]},
								"down": {"uv": [8, 29.5], "uv_size": [1, -6.5]}
							}
						},
						{
							"origin": [-0.53543, -7.56474, 7.09556],
							"size": [1.0625, 1.675, 6.5],
							"uv": {
								"north": {"uv": [37, 26], "uv_size": [1, 1.5]},
								"east": {"uv": [10, 16], "uv_size": [6.5, 1.5]},
								"south": {"uv": [37, 28], "uv_size": [1, 1.5]},
								"west": {"uv": [16, 10], "uv_size": [6.5, 1.5]},
								"up": {"uv": [9, 23], "uv_size": [1, 6.5]},
								"down": {"uv": [23, 23.5], "uv_size": [1, -6.5]}
							}
						},
						{
							"origin": [-0.50418, -9.75224, 13.59556],
							"size": [1, 3.8625, 0.5],
							"uv": {
								"north": {"uv": [1, 28], "uv_size": [1, 4]},
								"east": {"uv": [18, 36], "uv_size": [0.5, 4]},
								"south": {"uv": [2, 28], "uv_size": [1, 4]},
								"west": {"uv": [36, 18], "uv_size": [0.5, 4]},
								"up": {"uv": [42, 36], "uv_size": [1, 0.5]},
								"down": {"uv": [37, 42.5], "uv_size": [1, -0.5]}
							}
						},
						{
							"origin": [-0.53444, -8.98974, 11.08306],
							"size": [1.0605, 1.425, 2.5125],
							"uv": {
								"north": {"uv": [37, 31], "uv_size": [1, 1.5]},
								"east": {"uv": [28, 21], "uv_size": [2.5, 1.5]},
								"south": {"uv": [37, 34], "uv_size": [1, 1.5]},
								"west": {"uv": [28, 24], "uv_size": [2.5, 1.5]},
								"up": {"uv": [21, 31], "uv_size": [1, 2.5]},
								"down": {"uv": [22, 33.5], "uv_size": [1, -2.5]}
							}
						},
						{
							"origin": [-0.53444, -10.11474, 12.97681],
							"size": [1.0605, 1.125, 0.61875],
							"uv": {
								"north": {"uv": [35, 38], "uv_size": [1, 1]},
								"east": {"uv": [42, 37], "uv_size": [0.5, 1]},
								"south": {"uv": [38, 35], "uv_size": [1, 1]},
								"west": {"uv": [39, 42], "uv_size": [0.5, 1]},
								"up": {"uv": [42, 39], "uv_size": [1, 0.5]},
								"down": {"uv": [40, 42.5], "uv_size": [1, -0.5]}
							}
						},
						{
							"origin": [-0.53643, -7.93974, 6.93306],
							"size": [1.0645, 1.625, 6.825],
							"pivot": [0.15307, -7.05224, 7.93306],
							"rotation": [-22.5, 0, 0],
							"uv": {
								"north": {"uv": [36, 37], "uv_size": [1, 1.5]},
								"east": {"uv": [9, 12], "uv_size": [7, 1.5]},
								"south": {"uv": [37, 37], "uv_size": [1, 1.5]},
								"west": {"uv": [13, 0], "uv_size": [7, 1.5]},
								"up": {"uv": [12, 18], "uv_size": [1, 7]},
								"down": {"uv": [13, 25], "uv_size": [1, -7]}
							}
						},
						{
							"origin": [-0.51418, -7.53457, 6.82378],
							"size": [1.02, 1.85, 1],
							"uv": {
								"north": {"uv": [19, 36], "uv_size": [1, 2]},
								"east": {"uv": [20, 36], "uv_size": [1, 2]},
								"south": {"uv": [21, 36], "uv_size": [1, 2]},
								"west": {"uv": [22, 36], "uv_size": [1, 2]},
								"up": {"uv": [38, 36], "uv_size": [1, 1]},
								"down": {"uv": [38, 38], "uv_size": [1, -1]}
							}
						},
						{
							"origin": [-0.38918, -7.43457, 7.77378],
							"size": [0.77, 1.6, 1],
							"uv": {
								"north": {"uv": [0, 38], "uv_size": [1, 1.5]},
								"east": {"uv": [38, 0], "uv_size": [1, 1.5]},
								"south": {"uv": [1, 38], "uv_size": [1, 1.5]},
								"west": {"uv": [2, 38], "uv_size": [1, 1.5]},
								"up": {"uv": [38, 38], "uv_size": [1, 1]},
								"down": {"uv": [39, 1], "uv_size": [1, -1]}
							}
						},
						{
							"origin": [-0.50418, -7.5, 4.7],
							"size": [1, 1.85, 2.25],
							"pivot": [-0.05419, -7.2, 6.8],
							"rotation": [-22.5, 0, 0],
							"uv": {
								"north": {"uv": [36, 22], "uv_size": [1, 2]},
								"east": {"uv": [10, 25], "uv_size": [2.5, 2]},
								"south": {"uv": [24, 36], "uv_size": [1, 2]},
								"west": {"uv": [26, 0], "uv_size": [2.5, 2]},
								"up": {"uv": [23, 31], "uv_size": [1, 2.5]},
								"down": {"uv": [24, 33.5], "uv_size": [1, -2.5]}
							}
						},
						{
							"origin": [-0.49419, -7.38281, 5.80249],
							"size": [1, 1.75, 1.5],
							"pivot": [-0.04418, -7.73281, 5.00249],
							"rotation": [45, 0, 0],
							"uv": {
								"north": {"uv": [8, 36], "uv_size": [1, 2]},
								"east": {"uv": [29, 27], "uv_size": [1.5, 2]},
								"south": {"uv": [36, 8], "uv_size": [1, 2]},
								"west": {"uv": [4, 30], "uv_size": [1.5, 2]},
								"up": {"uv": [6, 37], "uv_size": [1, 1.5]},
								"down": {"uv": [7, 38.5], "uv_size": [1, -1.5]}
							}
						}
					]
				},
				{
					"name": "light_stock",
					"parent": "stocks",
					"pivot": [0, 0.15, -0.8],
					"cubes": [
						{
							"origin": [-0.45153, -5.82733, 13.30233],
							"size": [1, 1, 0.6],
							"pivot": [0.19847, -5.47733, 4.65233],
							"rotation": [0, 0, -45],
							"uv": {
								"north": {"uv": [39, 1], "uv_size": [1, 1]},
								"east": {"uv": [42, 40], "uv_size": [0.5, 1]},
								"south": {"uv": [39, 2], "uv_size": [1, 1]},
								"west": {"uv": [41, 42], "uv_size": [0.5, 1]},
								"up": {"uv": [42, 42], "uv_size": [1, 0.5]},
								"down": {"uv": [1, 43.5], "uv_size": [1, -0.5]}
							}
						},
						{
							"origin": [-0.37829, -5.82733, 7.65233],
							"size": [0.75, 0.75, 5.75],
							"pivot": [0.02171, -5.47733, 4.75233],
							"rotation": [0, 0, -45],
							"uv": {
								"north": {"uv": [39, 3], "uv_size": [1, 1]},
								"east": {"uv": [23, 10], "uv_size": [6, 1]},
								"south": {"uv": [39, 4], "uv_size": [1, 1]},
								"west": {"uv": [23, 11], "uv_size": [6, 1]},
								"up": {"uv": [4, 24], "uv_size": [1, 6]},
								"down": {"uv": [5, 30], "uv_size": [1, -6]}
							}
						},
						{
							"origin": [-0.76366, -9.18349, 13.86587],
							"size": [1.5, 4.69, 0.4],
							"uv": {
								"north": {"uv": [21, 0], "uv_size": [1.5, 4.5]},
								"east": {"uv": [12, 34], "uv_size": [0.5, 4.5]},
								"south": {"uv": [21, 17], "uv_size": [1.5, 4.5]},
								"west": {"uv": [23, 34], "uv_size": [0.5, 4.5]},
								"up": {"uv": [41, 15], "uv_size": [1.5, 0.5]},
								"down": {"uv": [41, 20.5], "uv_size": [1.5, -0.5]}
							}
						},
						{
							"origin": [-0.63866, -8.93349, 14.26587],
							"size": [1.25, 4.19, 0.4],
							"uv": {
								"north": {"uv": [24, 15], "uv_size": [1.5, 4]},
								"east": {"uv": [36, 24], "uv_size": [0.5, 4]},
								"south": {"uv": [16, 24], "uv_size": [1.5, 4]},
								"west": {"uv": [25, 36], "uv_size": [0.5, 4]},
								"up": {"uv": [21, 41], "uv_size": [1.5, 0.5]},
								"down": {"uv": [41, 21.5], "uv_size": [1.5, -0.5]}
							}
						},
						{
							"origin": [-0.63866, -6.68349, 7.26587],
							"size": [1.25, 1.94, 0.4],
							"uv": {
								"north": {"uv": [8, 30], "uv_size": [1.5, 2]},
								"east": {"uv": [6, 39], "uv_size": [0.5, 2]},
								"south": {"uv": [30, 14], "uv_size": [1.5, 2]},
								"west": {"uv": [7, 39], "uv_size": [0.5, 2]},
								"up": {"uv": [41, 23], "uv_size": [1.5, 0.5]},
								"down": {"uv": [25, 41.5], "uv_size": [1.5, -0.5]}
							}
						},
						{
							"origin": [-0.26366, -8.23849, 7.85087],
							"size": [0.5, 0.5, 6.035],
							"pivot": [-0.26366, -7.67349, 12.33587],
							"rotation": [-22.5, 0, 0],
							"uv": {
								"north": {"uv": [44, 5], "uv_size": [0.5, 0.5]},
								"east": {"uv": [30, 9], "uv_size": [6, 0.5]},
								"south": {"uv": [6, 44], "uv_size": [0.5, 0.5]},
								"west": {"uv": [30, 16], "uv_size": [6, 0.5]},
								"up": {"uv": [13, 30], "uv_size": [0.5, 6]},
								"down": {"uv": [18, 36], "uv_size": [0.5, -6]}
							}
						},
						{
							"origin": [-0.51286, -8.48849, 7.25087],
							"size": [1, 1, 0.71],
							"pivot": [-0.01286, -7.67349, 12.43587],
							"rotation": [-22.5, 0, 0],
							"uv": {
								"north": {"uv": [39, 5], "uv_size": [1, 1]},
								"east": {"uv": [43, 1], "uv_size": [0.5, 1]},
								"south": {"uv": [10, 39], "uv_size": [1, 1]},
								"west": {"uv": [2, 43], "uv_size": [0.5, 1]},
								"up": {"uv": [43, 2], "uv_size": [1, 0.5]},
								"down": {"uv": [3, 43.5], "uv_size": [1, -0.5]}
							}
						},
						{
							"origin": [-0.51286, -8.48849, 13.60087],
							"size": [1, 1, 0.71],
							"pivot": [-0.01286, -7.67349, 12.33587],
							"rotation": [-22.5, 0, 0],
							"uv": {
								"north": {"uv": [39, 10], "uv_size": [1, 1]},
								"east": {"uv": [4, 43], "uv_size": [0.5, 1]},
								"south": {"uv": [11, 39], "uv_size": [1, 1]},
								"west": {"uv": [43, 4], "uv_size": [0.5, 1]},
								"up": {"uv": [5, 43], "uv_size": [1, 0.5]},
								"down": {"uv": [43, 5.5], "uv_size": [1, -0.5]}
							}
						},
						{
							"origin": [-0.51418, -6.63457, 6.32378],
							"size": [1.02, 1.85, 1],
							"uv": {
								"north": {"uv": [26, 36], "uv_size": [1, 2]},
								"east": {"uv": [27, 36], "uv_size": [1, 2]},
								"south": {"uv": [28, 36], "uv_size": [1, 2]},
								"west": {"uv": [36, 28], "uv_size": [1, 2]},
								"up": {"uv": [39, 11], "uv_size": [1, 1]},
								"down": {"uv": [12, 40], "uv_size": [1, -1]}
							}
						},
						{
							"origin": [-0.38918, -6.53457, 7.27378],
							"size": [0.77, 1.6, 1],
							"uv": {
								"north": {"uv": [3, 38], "uv_size": [1, 1.5]},
								"east": {"uv": [4, 38], "uv_size": [1, 1.5]},
								"south": {"uv": [5, 38], "uv_size": [1, 1.5]},
								"west": {"uv": [8, 38], "uv_size": [1, 1.5]},
								"up": {"uv": [39, 12], "uv_size": [1, 1]},
								"down": {"uv": [39, 14], "uv_size": [1, -1]}
							}
						},
						{
							"origin": [-0.50418, -6.6, 4.2],
							"size": [1, 1.85, 2.25],
							"pivot": [-0.05419, -6.3, 6.3],
							"rotation": [-22.5, 0, 0],
							"uv": {
								"north": {"uv": [29, 36], "uv_size": [1, 2]},
								"east": {"uv": [26, 2], "uv_size": [2.5, 2]},
								"south": {"uv": [30, 36], "uv_size": [1, 2]},
								"west": {"uv": [26, 4], "uv_size": [2.5, 2]},
								"up": {"uv": [31, 24], "uv_size": [1, 2.5]},
								"down": {"uv": [25, 33.5], "uv_size": [1, -2.5]}
							}
						}
					]
				},
				{
					"name": "magazine",
					"parent": "gun_body",
					"pivot": [0, -7.76376, 3.0287]
				},
				{
					"name": "sliding_magazine",
					"parent": "magazine",
					"pivot": [3.69472, -3.22843, 3.01483],
					"cubes": [
						{
							"origin": [0.63222, -3.54093, 1.76483],
							"size": [4.5, 0.75, 2.5],
							"uv": {
								"north": {"uv": [26, 6], "uv_size": [4.5, 1]},
								"east": {"uv": [31, 17], "uv_size": [2.5, 1]},
								"south": {"uv": [26, 17], "uv_size": [4.5, 1]},
								"west": {"uv": [31, 22], "uv_size": [2.5, 1]},
								"up": {"uv": [0, 8], "uv_size": [4.5, 2.5]},
								"down": {"uv": [5, 10.5], "uv_size": [4.5, -2.5]}
							}
						},
						{
							"origin": [0.13222, -3.44093, 1.86483],
							"size": [0.5, 0.55, 2.3],
							"uv": {
								"north": {"uv": [29, 13], "uv_size": [0.5, 0.5]},
								"east": {"uv": [44, 13], "uv_size": [2.5, 0.5]},
								"south": {"uv": [30, 13], "uv_size": [0.5, 0.5]},
								"west": {"uv": [14, 44], "uv_size": [2.5, 0.5]},
								"up": {"uv": [29, 10], "uv_size": [0.5, 2.5]},
								"down": {"uv": [30, 12.5], "uv_size": [0.5, -2.5]}
							}
						},
						{
							"origin": [5.63222, -3.29093, 1.76483],
							"size": [1, 0, 2.5],
							"uv": {
								"north": {"uv": [0, 0], "uv_size": [1, 0]},
								"east": {"uv": [0, 0], "uv_size": [2.5, 0]},
								"south": {"uv": [0, 0], "uv_size": [1, 0]},
								"west": {"uv": [0, 0], "uv_size": [2.5, 0]},
								"up": {"uv": [26, 31], "uv_size": [1, 2.5]}
							}
						},
						{
							"origin": [5.13222, -3.79093, 1.76483],
							"size": [0.5, 1, 2.5],
							"uv": {
								"north": {"uv": [8, 43], "uv_size": [0.5, 1]},
								"east": {"uv": [31, 30], "uv_size": [2.5, 1]},
								"south": {"uv": [43, 8], "uv_size": [0.5, 1]},
								"west": {"uv": [31, 31], "uv_size": [2.5, 1]},
								"up": {"uv": [16, 38], "uv_size": [0.5, 2.5]},
								"down": {"uv": [38, 18.5], "uv_size": [0.5, -2.5]}
							}
						}
					]
				},
				{
					"name": "left_arm",
					"parent": "magazine",
					"pivot": [6, -1.9432, 6.20305],
					"cubes": [
						{
							"origin": [4.75, -7.7432, 4.95305],
							"size": [2.5, 10, 2.5],
							"uv": {
								"north": {"uv": [0, 0], "uv_size": [0.5, 0.5]},
								"east": {"uv": [0, 0], "uv_size": [0.5, 0.5]},
								"south": {"uv": [0, 0], "uv_size": [0.5, 0.5]},
								"west": {"uv": [0, 0], "uv_size": [0.5, 0.5]},
								"up": {"uv": [0.5, 0.5], "uv_size": [-0.5, -0.5]},
								"down": {"uv": [0.5, 0.5], "uv_size": [-0.5, -0.5]}
							}
						}
					]
				},
				{
					"name": "attachment_bone",
					"parent": "gun_body",
					"pivot": [-0.00188, -6.57875, 3.44059]
				},
				{
					"name": "right_arm",
					"parent": "gun_body",
					"pivot": [-6, -3.9432, 6.20305],
					"cubes": [
						{
							"origin": [-7.25, -7.7432, 4.95305],
							"size": [2.5, 10, 2.5],
							"uv": {
								"north": {"uv": [0, 0], "uv_size": [0.5, 0.5]},
								"east": {"uv": [0, 0], "uv_size": [0.5, 0.5]},
								"south": {"uv": [0, 0], "uv_size": [0.5, 0.5]},
								"west": {"uv": [0, 0], "uv_size": [0.5, 0.5]},
								"up": {"uv": [0.5, 0.5], "uv_size": [-0.5, -0.5]},
								"down": {"uv": [0.5, 0.5], "uv_size": [-0.5, -0.5]}
							}
						}
					]
				}
			]
		}
	]
}